django_nimbus_api/LICENSE.txt
django_nimbus_api/__init__.py
django_nimbus_api/admin.py
django_nimbus_api/apps.py
django_nimbus_api/code.py
django_nimbus_api/des.py
django_nimbus_api/err_code.py
django_nimbus_api/exceptions.py
django_nimbus_api/fields.py
django_nimbus_api/filters.py
django_nimbus_api/models.py
django_nimbus_api/parsers.py
django_nimbus_api/permissions.py
django_nimbus_api/renderers.py
django_nimbus_api/serializers.py
django_nimbus_api/settings.py
django_nimbus_api/tests.py
django_nimbus_api/throttling.py
django_nimbus_api/urls.py
django_nimbus_api/utility.py
django_nimbus_api/utils.py
django_nimbus_api/validators.py
django_nimbus_api/versioning.py
django_nimbus_api/authentication/__init__.py
django_nimbus_api/authentication/auth_jwt.py
django_nimbus_api/authentication/auth_token.py
django_nimbus_api/jwt_handler/__init__.py
django_nimbus_api/jwt_handler/handler.py
django_nimbus_api/locale/en/LC_MESSAGES/django.po
django_nimbus_api/locale/zh/LC_MESSAGES/django.po
django_nimbus_api/migrations/__init__.py
django_nimbus_api/pagination/__init__.py
django_nimbus_api/pagination/base.py
django_nimbus_api/pagination/full.py
django_nimbus_api/views/__init__.py
django_nimbus_api/views/handler.py
django_nimbus_api/views/schemas.py
django_nimbus_api/views/swagger.py
django_nimbus_api-3.3.0.dist-info/LICENSE.md
django_nimbus_api-3.3.0.dist-info/METADATA
django_nimbus_api-3.3.0.dist-info/WHEEL
django_nimbus_api-3.3.0.dist-info/top_level.txt
django_nimbus_api-3.3.0.dist-info/RECORD
